tag_creator/__init__.py
tag_creator/__main__.py
tag_creator/arguments.py
tag_creator/configuration.py
tag_creator/configuration.yml
tag_creator/logger.py
tag_creator/repository/batch_version.py
tag_creator/repository/git.py
tag_creator/repository/version.py
tag_creator/utils/shell.py
tag_creator-0.1.1.dist-info/LICENSE
tag_creator-0.1.1.dist-info/METADATA
tag_creator-0.1.1.dist-info/WHEEL
tag_creator-0.1.1.dist-info/top_level.txt
tag_creator-0.1.1.dist-info/RECORD
