Metadata-Version: 2.2
Name: tag_creator
Version: 0.1.1
Summary: Automatically create git release tags based on a merged commit message and previous tag.
Author-email: Vladyslav Honcharenko <goncharvlad02@gmail.com>
Maintainer-email: Vladyslav Honcharenko <goncharvlad02@gmail.com>
License: MIT License
Project-URL: Repository, https://github.com/Oberstmarschall/tag_creator
Keywords: git,tag,create git tag,git release tag,semver tag
Classifier: Programming Language :: Python :: 3.11
Requires-Python: >=3.11
License-File: LICENSE
Requires-Dist: PyYAML==6.0.2
